{
"":["diffServConfigMib"],
".1":["diffServConfigMIBObjects"],
".1.2":["diffServConfigTable"],
".1.2.1":["diffServConfigEntry"],
".1.2.1.1":["diffServConfigId"],
".1.2.1.2":["diffServConfigDescr"],
".1.2.1.3":["diffServConfigOwner"],
".1.2.1.4":["diffServConfigLastChange"],
".1.2.1.5":["diffServConfigStart"],
".1.2.1.6":["diffServConfigStorage"],
".1.2.1.7":["diffServConfigStatus"],
".2":["diffServConfigMIBConformance"],
".2.1":["diffServConfigMIBCompliances"],
".2.1.1":["diffServConfigMIBFullCompliance"],
".2.2":["diffServConfigMIBGroups"],
".2.2.1":["diffServConfigMIBConfigGroup"]
}